pg_fts/fields.py
pg_fts/introspection.py
pg_fts/__init__.py
pg_fts/utils.py
pg_fts/aggregates.py
pg_fts/migrations.py
pg_fts/models.py
pg_fts/ranks.py
django_pg_fts-0.1.1.dist-info/DESCRIPTION.rst
django_pg_fts-0.1.1.dist-info/metadata.json
django_pg_fts-0.1.1.dist-info/RECORD
django_pg_fts-0.1.1.dist-info/WHEEL
django_pg_fts-0.1.1.dist-info/top_level.txt
django_pg_fts-0.1.1.dist-info/METADATA
