Metadata-Version: 2.0
Name: django-pg-fts
Version: 0.1.1
Summary: Implementation of PostgreSQL Full Text Search for django 1.7
Home-page: http://www.dvdmgl.com/
Author: dvdmgl
Author-email: dvdmgl@gmail.com
License: BSD License
Keywords: django postgres postgresql pgsql full text search fts
Platform: UNKNOWN
Classifier: Development Status :: 3 - Alpha
Classifier: Environment :: Web Environment
Classifier: Framework :: Django
Classifier: Intended Audience :: Developers
Classifier: License :: OSI Approved :: BSD License
Classifier: Operating System :: OS Independent
Classifier: Programming Language :: Python :: 2
Classifier: Programming Language :: Python :: 2.7
Classifier: Programming Language :: Python :: 3
Classifier: Programming Language :: Python :: 3.3
Classifier: Programming Language :: Python :: 3.4
Classifier: Programming Language :: Python :: 2.7
Classifier: Topic :: Internet :: WWW/HTTP
Classifier: Topic :: Internet :: WWW/HTTP :: Dynamic Content
Requires: Django (>=1.7)
Requires: psycopg2
